iterart/__init__.py
iterart/shared.py
iterart/attractors/__init__.py
iterart/attractors/clifford.py
iterart/nebulabrot/__init__.py
iterart/nebulabrot/kernel.py
iterart/nebulabrot/render.py
iterart-0.5.0.dist-info/licenses/LICENSE
iterart-0.5.0.dist-info/METADATA
iterart-0.5.0.dist-info/WHEEL
iterart-0.5.0.dist-info/top_level.txt
iterart-0.5.0.dist-info/RECORD
