Metadata-Version: 2.4
Name: iterart
Version: 0.5.0
Summary: A collection of tools to generate renderings based on iterative functions.
Home-page: https://github.com/karzunn/iterart
Author: Carson O'Ffill
Author-email: offillcarson@gmail.com
License: MIT
Classifier: Programming Language :: Python :: 3.10
Classifier: Programming Language :: Python :: 3.11
Classifier: Programming Language :: Python :: 3.12
Classifier: Programming Language :: Python :: 3.13
Classifier: Operating System :: OS Independent
Requires-Python: >=3.10
License-File: LICENSE
Requires-Dist: pyopencl>=2025.1
Requires-Dist: numpy>=2.1.3
Requires-Dist: pillow>=11.1.0
Dynamic: author
Dynamic: author-email
Dynamic: classifier
Dynamic: description
Dynamic: description-content-type
Dynamic: home-page
Dynamic: license
Dynamic: license-file
Dynamic: requires-dist
Dynamic: requires-python
Dynamic: summary
